tvbox/__init__.py
tvbox/config.py
tvbox/item.py
tvbox/loader.py
tvbox/run.py
tvbox/scanner.py
tvbox/source.py
tvbox/sync.py
tvbox/lives/__init__.py
tvbox/lives/channel.py
tvbox/lives/factory.py
tvbox/lives/genre.py
tvbox/lives/parser.py
tvbox/lives/scanner.py
tvbox/lives/stream.py
tvbox/lives/translate.py
tvbox/types/__init__.py
tvbox/types/dictionary.py
tvbox/utils/__init__.py
tvbox/utils/aio.py
tvbox/utils/crypto.py
tvbox/utils/log.py
tvbox/utils/runner.py
tvbox-1.0.0.dist-info/METADATA
tvbox-1.0.0.dist-info/WHEEL
tvbox-1.0.0.dist-info/entry_points.txt
tvbox-1.0.0.dist-info/top_level.txt
tvbox-1.0.0.dist-info/RECORD
