Metadata-Version: 2.1
Name: tvbox
Version: 1.0.0
Summary: TV Box: Live Stream
Home-page: https://github.com/moky/TVBox
Author: Albert Moky
Author-email: albert.moky@gmail.com
License: MIT
Platform: UNKNOWN
Classifier: Programming Language :: Python :: 3
Classifier: License :: OSI Approved :: MIT License
Classifier: Operating System :: OS Independent
Requires-Dist: aiohttp
Requires-Dist: aiou (>=0.3.0)
